{
  "1": {
    "width": 10,
    "height": 10,
    "map": "########## #G.......# #........# #........# #........# #........# #...S....# #........# #...P....# ##########"
  },
  "2": {
    "width": 8,
    "height": 8,
    "map": "#########......##......##..##..##.S##..##..##..##.P##.G#########"
  },
  "3": {
    "width": 19,
    "height": 20,
    "map": "####################.................##.................##.....#####.......##.....#.E.........##.....#####.......##.......E.#.......##....######.......##....#............##....#............##....#............##....#.E..........##....#............##....####.........##....#.G#.........##....#..####...#..##.S..#.........#..##....#.........#..##.P..#.........#..####################"
  }
}